actfw_jetson/__init__.py
actfw_jetson/camera.py
actfw_jetson/display.py
actfw_jetson/logger.py
actfw_jetson-0.1.3.dist-info/LICENSE.txt
actfw_jetson-0.1.3.dist-info/WHEEL
actfw_jetson-0.1.3.dist-info/METADATA
actfw_jetson-0.1.3.dist-info/RECORD
