Metadata-Version: 2.1
Name: actfw-jetson
Version: 0.1.3
Summary: actfw's additional components for Jetson series
Home-page: https://github.com/Idein/actfw-jetson
License: MIT
Keywords: actcast
Author: Idein Inc.
Requires-Python: >=3.6.2,<4.0.0
Classifier: Development Status :: 4 - Beta
Classifier: Intended Audience :: Developers
Classifier: License :: OSI Approved :: MIT License
Classifier: Programming Language :: Python :: 3
Classifier: Programming Language :: Python :: 3 :: Only
Classifier: Programming Language :: Python :: 3.10
Classifier: Programming Language :: Python :: 3.7
Classifier: Programming Language :: Python :: 3.8
Classifier: Programming Language :: Python :: 3.9
Requires-Dist: Pillow (>=5,<6)
Requires-Dist: PyGObject (>=3.26.1,<4.0.0)
Requires-Dist: actfw-core (>=2.1.1,<3.0.0)
Project-URL: Repository, https://github.com/Idein/actfw-jetson
